conda_workon.py
conda_workon-0.4.0.dist-info/DESCRIPTION.rst
conda_workon-0.4.0.dist-info/METADATA
conda_workon-0.4.0.dist-info/RECORD
conda_workon-0.4.0.dist-info/WHEEL
conda_workon-0.4.0.dist-info/entry_points.txt
conda_workon-0.4.0.dist-info/metadata.json
conda_workon-0.4.0.dist-info/top_level.txt
