Metadata-Version: 2.0
Name: conda-workon
Version: 0.4.0
Summary: Activate conda environments in subshells
Home-page: https://bitbucket.org/flub/conda-workon
Author: Floris Bruynooghe
Author-email: flub@devork.be
License: BSD
Platform: UNKNOWN
Classifier: Development Status :: 3 - Alpha
Classifier: Intended Audience :: Developers
Classifier: Operating System :: OS Independent
Classifier: Programming Language :: Python :: 2
Classifier: Programming Language :: Python :: 3
Classifier: Environment :: Console
Requires-Dist: conda
Provides-Extra: yaml
Requires-Dist: PyYAML; extra == 'yaml'
